icomo/__init__.py
icomo/_version.py
icomo/comp_model.py
icomo/diffrax_wrapper.py
icomo/jax2pytensor.py
icomo/tree_tools.py
icomo/experimental/__init__.py
icomo/experimental/slow_modulation.py
icomo/experimental/tools.py
icomo-1.0.3.dist-info/LICENSE
icomo-1.0.3.dist-info/METADATA
icomo-1.0.3.dist-info/WHEEL
icomo-1.0.3.dist-info/top_level.txt
icomo-1.0.3.dist-info/RECORD
