Metadata-Version: 2.2
Name: icomo
Version: 1.0.3
Summary: This toolbox aims to simplify the construction of compartmental models and the inference of their parameters
Author-email: Jonas Dehning <jonas.dehning@ds.mpg.de>
Project-URL: Homepage, https://github.com/Priesemann-Group/icomo
Project-URL: Bug Tracker, https://github.com/Priesemann-Group/icomo/issues
Project-URL: Discussions, https://github.com/Priesemann-Group/icomo/discussions
Project-URL: Changelog, https://github.com/Priesemann-Group/icomo/releases
Classifier: License :: OSI Approved :: MIT License
Classifier: Programming Language :: Python
Classifier: Programming Language :: Python :: 3
Classifier: Programming Language :: Python :: 3 :: Only
Classifier: Programming Language :: Python :: 3.10
Classifier: Programming Language :: Python :: 3.11
Classifier: Programming Language :: Python :: 3.12
Requires-Python: >=3.10
License-File: LICENSE
Requires-Dist: pymc==5.*
Requires-Dist: equinox
Requires-Dist: diffrax
Requires-Dist: pytensor
Requires-Dist: graphviz
Requires-Dist: jax
Requires-Dist: numpy
Provides-Extra: opt
Requires-Dist: numpyro; extra == "opt"
Requires-Dist: optax; extra == "opt"
Requires-Dist: jaxopt; extra == "opt"
Requires-Dist: equinox; extra == "opt"
Requires-Dist: jaxtyping; extra == "opt"
Requires-Dist: optimistix; extra == "opt"
Provides-Extra: dev
Requires-Dist: icomo[opt]; extra == "dev"
Requires-Dist: pytest>=7.3.2; extra == "dev"
Requires-Dist: pytest-xdist; extra == "dev"
Requires-Dist: pre-commit>=3.3.2; extra == "dev"
Requires-Dist: ruff>=0.0.272; extra == "dev"
Requires-Dist: ipykernel>=6.0.0; extra == "dev"
Requires-Dist: Sphinx>=6.2.1; extra == "dev"
Requires-Dist: sphinx-book-theme; extra == "dev"
Requires-Dist: importlib-metadata>=6.5.1; extra == "dev"
Requires-Dist: myst-parser>=0.19.2; extra == "dev"
Requires-Dist: nbsphinx>=0.9.2; extra == "dev"
Requires-Dist: pandoc>=2.3; extra == "dev"
Requires-Dist: pytest-beartype; extra == "dev"
Requires-Dist: sphinx-autodoc-typehints; extra == "dev"
